rushconsole/__init__.py
rushconsole/choice.py
rushconsole/result.py
rushconsole-0.1.1.dist-info/licenses/LICENSE.txt
scripts/build.py
scripts/install.py
rushconsole-0.1.1.dist-info/METADATA
rushconsole-0.1.1.dist-info/WHEEL
rushconsole-0.1.1.dist-info/top_level.txt
rushconsole-0.1.1.dist-info/RECORD
