Metadata-Version: 2.4
Name: rushconsole
Version: 0.1.1
Summary: python console
Home-page: https://github.com/meatdumplings0019/rushconsole
Author: ndrzy
Author-email: ndrzy <dandan0019@outlook.com>
License: MIT
Project-URL: Homepage, https://github.com/meatdumplings0019/rushconsole
Requires: questionary
Requires-Python: >=3.10
License-File: LICENSE.txt
Requires-Dist: questionary
Dynamic: author
Dynamic: home-page
Dynamic: license-file
Dynamic: requires
Dynamic: requires-python
